massedit.py
massedit-0.71.0.dist-info/licenses/LICENSE.txt
massedit-0.71.0.dist-info/METADATA
massedit-0.71.0.dist-info/WHEEL
massedit-0.71.0.dist-info/entry_points.txt
massedit-0.71.0.dist-info/top_level.txt
massedit-0.71.0.dist-info/RECORD
