Metadata-Version: 2.4
Name: massedit
Version: 0.71.0
Summary: Edit multiple files using Python text processing modules
Author-email: elmotec <elmotec@gmx.com>
License: MIT
Project-URL: Homepage, http://github.com/elmotec/massedit
Keywords: sed,editor,stream,python,edit,mass
Classifier: Development Status :: 5 - Production/Stable
Classifier: License :: OSI Approved :: MIT License
Classifier: Environment :: Console
Classifier: Natural Language :: English
Classifier: Programming Language :: Python :: 3.10
Classifier: Programming Language :: Python :: 3.11
Classifier: Programming Language :: Python :: 3.12
Classifier: Programming Language :: Python :: 3.13
Classifier: Topic :: Software Development
Classifier: Topic :: Software Development :: Code Generators
Classifier: Topic :: Text Editors :: Text Processing
Classifier: Topic :: Text Processing :: Filters
Classifier: Topic :: Utilities
Classifier: Intended Audience :: Developers
Requires-Python: >=3.10
License-File: LICENSE.txt
Provides-Extra: develop
Requires-Dist: black; extra == "develop"
Requires-Dist: commitizen; extra == "develop"
Requires-Dist: flake8; extra == "develop"
Requires-Dist: pre-commit; extra == "develop"
Requires-Dist: pylint; extra == "develop"
Requires-Dist: pytest; extra == "develop"
Dynamic: license-file
